proxy_lib/__init__.py
proxy_lib/proxy_utils.py
html_lib_proxy-0.2.dist-info/METADATA
html_lib_proxy-0.2.dist-info/WHEEL
html_lib_proxy-0.2.dist-info/top_level.txt
html_lib_proxy-0.2.dist-info/RECORD
